{
  "doc_id": "form_iacuc_animal_care_program_checklist",
  "title": "Animal Care Program Checklist",
  "category": "form",
  "subcategory": "iacuc_form",
  "display_label": "IACUC \u2014 Animal Care Program Checklist",
  "source_url": "https://www.morgan.edu/office-of-research-administration/research-compliance/animal-research/iacuc-forms",
  "procedure_url": "https://www.morgan.edu/Documents/ADMINISTRATION/DIVISIONS/RED/2021/Animal%20Research/IACUS%20FORMS/Animal%20Care%20Program%20Checklist%20(annual%20review%20items).docx",
  "content": "IACUC checklist of annual-review items for the Animal Care Program covering policies, training records, facility inspection, and compliance documentation.",
  "last_scraped": "2026-05-14",
  "playwright_verified": true,
  "playwright_verified_at": "2026-05-14"
}
