{
  "doc_id": "form_coi_educational_slide_deck",
  "title": "COI Educational Slide Deck",
  "category": "form",
  "subcategory": "compliance_pdf",
  "display_label": "COI Educational Slide Deck (PowerPoint)",
  "source_url": "https://www.morgan.edu/office-of-research-administration/research-compliance/conflict-of-interest-x12058",
  "procedure_url": "https://www.morgan.edu/Documents/ADMINISTRATION/OFFICES/ott/COI-EduSlideDeck.pptx",
  "content": "Microsoft PowerPoint presentation introducing Morgan personnel to COI concepts in R&D — disclosable interests, the disclosure workflow, common scenarios, and management strategies. Suitable for self-study or departmental training sessions.",
  "last_scraped": "2026-05-14"
}
