{
  "doc_id": "form_irb_process_synopsis",
  "title": "IRB Process Synopsis",
  "category": "research_compliance",
  "subcategory": "compliance_pdf",
  "display_label": "IRB Process Synopsis (Guidance)",
  "source_url": "https://www.morgan.edu/office-of-research-administration/research-compliance/human-subjects-research",
  "procedure_url": "https://www.morgan.edu/Documents/ADMINISTRATION/OFFICES/ora/IRB%20Forms/2023-03-21_IRB_Process_Synopsis.pdf",
  "content": "Guidance PDF (dated 2023-03-21) summarizing the Morgan State IRB review workflow end-to-end — what to submit, how reviews are routed (exempt, expedited, full board), timelines, and approval outcomes. Intended as a first-stop reference for new PIs.",
  "last_scraped": "2026-05-14",
  "legacy_category": "form"
}