{
  "doc_id": "course_cosc_458",
  "title": "Course: COSC 458 - Software Engineering",
  "category": "academic",
  "subcategory": "course_detail",
  "course_code": "COSC 458",
  "course_name": "Software Engineering",
  "credits": 3,
  "prerequisites_text": "COSC 220 (Grade C or higher)",
  "prerequisite_codes": [
    "COSC 220"
  ],
  "offered": "Fall, Spring",
  "content": "COSC 458 - Software Engineering\nCredits: 3\nPrerequisites: COSC 220 (Grade C or higher)\nOffered: Fall, Spring",
  "source_file": "academic_courses.txt"
}